[
	{
		"pid":"02001",
		"imgSrc":"../images/551d961bb772e1779762d042ef8f4688_303x303M.jpg",
		"pName":"雅兰床垫 BEVIS 软硬双选 护脊弹簧",
		"desc":"软硬舒适两用款 办公族护脊 精钢五环护脊弹簧",
		"price":"2799",
		"yprice":"6365",
		"count":"35"
	},
	{
		"pid":"02002",
		"imgSrc":"../images/f09739f6b6070727fcf3447a179541b6_303x303M.jpg",
		"pName":"雅兰床垫 BEVIS 软硬双选 护脊弹簧",
		"desc":"软硬舒适两用款 办公族护脊 精钢五环护脊弹簧",
		"price":"2799",
		"yprice":"6365",
		"count":"35"
	},
	{
		"pid":"02003",
		"imgSrc":"../images/5114de936c90a1eece4aaa505e5b3e22_303x303M.jpg",
		"pName":"雅兰床垫 BEVIS 软硬双选 护脊弹簧",
		"desc":"软硬舒适两用款 办公族护脊 精钢五环护脊弹簧",
		"price":"2799",
		"yprice":"6365",
		"count":"35"
	},
	{
		"pid":"02004",
		"imgSrc":"../images/5c3042122c0eebb57ec6d63023bc91dd_303x303M.jpg",
		"pName":"雅兰床垫 BEVIS 软硬双选 护脊弹簧",
		"desc":"软硬舒适两用款 办公族护脊 精钢五环护脊弹簧",
		"price":"2799",
		"yprice":"6365",
		"count":"35"
	},
	{
		"pid":"02005",
		"imgSrc":"../images/88a7a2e08dea207d80dbb12070b093da_303x303M.jpg",
		"pName":"雅兰床垫 BEVIS 软硬双选 护脊弹簧",
		"desc":"软硬舒适两用款 办公族护脊 精钢五环护脊弹簧",
		"price":"2799",
		"yprice":"6365",
		"count":"35"
	},
	{
		"pid":"02006",
		"imgSrc":"../images/b39af20ae62d4ef45f06e9af9bf61242_303x303M.jpg",
		"pName":"雅兰床垫 BEVIS 软硬双选 护脊弹簧",
		"desc":"软硬舒适两用款 办公族护脊 精钢五环护脊弹簧",
		"price":"2799",
		"yprice":"6365",
		"count":"35"
	},
	{
		"pid":"02007",
		"imgSrc":"../images/551d961bb772e1779762d042ef8f4688_303x303M.jpg",
		"pName":"雅兰床垫 BEVIS 软硬双选 护脊弹簧",
		"desc":"软硬舒适两用款 办公族护脊 精钢五环护脊弹簧",
		"price":"2799",
		"yprice":"6365",
		"count":"35"
	},
	{
		"pid":"02008",
		"imgSrc":"../images/f09739f6b6070727fcf3447a179541b6_303x303M.jpg",
		"pName":"雅兰床垫 BEVIS 软硬双选 护脊弹簧",
		"desc":"软硬舒适两用款 办公族护脊 精钢五环护脊弹簧",
		"price":"2799",
		"yprice":"6365",
		"count":"35"
	},
	{
		"pid":"02009",
		"imgSrc":"../images/5114de936c90a1eece4aaa505e5b3e22_303x303M.jpg",
		"pName":"雅兰床垫 BEVIS 软硬双选 护脊弹簧",
		"desc":"软硬舒适两用款 办公族护脊 精钢五环护脊弹簧",
		"price":"2799",
		"yprice":"6365",
		"count":"35"
	},
	{
		"pid":"02010",
		"imgSrc":"../images/5c3042122c0eebb57ec6d63023bc91dd_303x303M.jpg",
		"pName":"雅兰床垫 BEVIS 软硬双选 护脊弹簧",
		"desc":"软硬舒适两用款 办公族护脊 精钢五环护脊弹簧",
		"price":"2799",
		"yprice":"6365",
		"count":"35"
	},
	{
		"pid":"02011",
		"imgSrc":"../images/88a7a2e08dea207d80dbb12070b093da_303x303M.jpg",
		"pName":"雅兰床垫 BEVIS 软硬双选 护脊弹簧",
		"desc":"软硬舒适两用款 办公族护脊 精钢五环护脊弹簧",
		"price":"2799",
		"yprice":"6365",
		"count":"35"
	},
	{
		"pid":"02012",
		"imgSrc":"../images/b39af20ae62d4ef45f06e9af9bf61242_303x303M.jpg",
		"pName":"雅兰床垫 BEVIS 软硬双选 护脊弹簧",
		"desc":"软硬舒适两用款 办公族护脊 精钢五环护脊弹簧",
		"price":"2799",
		"yprice":"6365",
		"count":"35"
	}
]
